{
  "questions" :
  [
    {
    "answers_list" : [ "Агент Картер", "Агенты Щ.И.Т.А.", "Нелюди", "Защитники" ],
    "correct_answer" : "Агент Картер",
    "question" : "В каком сериале впервые упоминался Гравитониум"
    },
    {
	
    "answers_list" : [ "Бакки Барнса", "Стива Роджерс", "Альтрона", "Локи" ],
    "correct_answer" : "Бакки Барнса",
    "question" : "Кого хотел убить Тони Старк в Гражданской войне"
    },
	
	    {
    "answers_list" : [ "Лиз Аллен", "Мэри Джейн", "Гвен Стейси", "Мэй Паркер" ],
    "correct_answer" : "Лиз Аллен",
    "question" : "Как звали первую любовь питера паркера в Киновселенной Марвел"
    },
	
	    {
    "answers_list" : [ "Йоган Шмидт", "Баки Барнс", "Вольфганг фон Стракер", "Гидеон Малик" ],
    "correct_answer" : "Йоган Шмидт",
    "question" : "Настоящее имя красного черепа"
    },
	
	    {
    "answers_list" : [ "М-16", "АК-47", "Секира", "Меч" ],
    "correct_answer" : "М-16",
    "question" : "Любимое оружие Скерджа (Палача)"
    }
  ]
}